{
  "log":{},
  "dns":{},
  "stats":{},
  "inbounds":[
    {
      "port":"1080",
      "protocol":"socks",
      "settings":{
        "auth":"noauth",
        "udp":true
      },
      "tag":"in-0"
    },
    {
      "port":"1081",
      "protocol":"http",
      "settings":{},
      "tag":"in-1"
    }
  ],
  "outbounds":[
    {
      "protocol":"vmess",
      "settings":{
        "vnext":[
          {
            "address":"iffy.me",
            "port":3333,
            "users":[
              {
                "id":"02fb1728-d04a-434f-a527-bceffabd31d1",
                "alterId":32
              }
            ]
          }
        ]
      },
      "tag":"out-0",
      "streamSettings":{
        "network":"ws",
        "security":"tls",
        "wsSettings":{
          "path":"/websocket_message"
        },
        "tlsSettings":{
          "serverName":"iffy.me"
        }
      }
    },
    {
      "tag":"direct",
      "protocol":"freedom",
      "settings":{}
    },
    {
      "tag":"blocked",
      "protocol":"blackhole",
      "settings":{}
    }
  ],
  "routing":{
    "domainStrategy":"IPOnDemand",
    "rules":[
      {
        "type":"field",
        "ip":[
          "geoip:private"
        ],
        "outboundTag":"direct"
      }
    ]
  },
  "policy":{},
  "reverse":{},
  "transport":{}
}